ahp_gaussiano/__init__.py
ahp_gaussiano/ahp.py
tests/__init__.py
tests/test_ahp.p.py
ahp_gaussiano-0.1.2.dist-info/METADATA
ahp_gaussiano-0.1.2.dist-info/WHEEL
ahp_gaussiano-0.1.2.dist-info/top_level.txt
ahp_gaussiano-0.1.2.dist-info/RECORD
