Metadata-Version: 2.1
Name: ahp_gaussiano
Version: 0.1.2
Summary: Pacote para cálculo de AHP Gaussiano
Home-page: https://github.com/BrunoMeloSlv/ahp_gaussiano
Author: Bruno Melo
Author-email: Brunomeloslv@gmail.com
Classifier: Programming Language :: Python :: 3
Classifier: License :: OSI Approved :: MIT License
Classifier: Operating System :: OS Independent
Requires-Python: >=3.6
Requires-Dist: pandas
Requires-Dist: numpy
